Workbook

Sheet Portada
B1: Cuestionario de Madurez en Ciberseguridad — Kudo
B2: Cuestionario Completo (agrupa los ámbitos Interno, de Terceros y Externo)
B4: Objetivo
B5: Este cuestionario es un ejercicio mayéutico de autoevaluación, no un examen de pasar/fallar. La ciberseguridad no es binaria: cada requisito debe interpretarse a la luz del apetito de riesgo, el tamaño, la estrategia y el momento de negocio de tu organización.
B7: Cómo usar este archivo
B8: 1. Ve a la pestaña "Cuestionario - Completo".
B9: 2. Para cada uno de los 491 requisitos, selecciona en la columna "Respuesta (0-5)" un valor de la lista desplegable, según el nivel de madurez real de tu organización frente a ese requisito.
B10: 3. Las columnas "% Cumplimiento" y "Nivel de Madurez" de cada fila se calculan automáticamente.
B11: 4. Ve a la pestaña "Resultado - Completo" para ver el nivel de madurez global y el desglose por dominio, calculado en vivo a partir de tus respuestas.
B12: 5. Consulta la pestaña "Escala" para el detalle de la escala 0-5, y "Rangos de Madurez" para la interpretación de los porcentajes finales.
B14: Escala por pregunta (0 a 5)
B15: Cada pregunta se califica en una escala de 0 a 5, donde cada punto representa un incremento del 20% del nivel máximo de madurez. Ver hoja "Escala".
... B24: Generado a partir del catálogo OSCAL de Kudo (content/framework/oscal/kudo/rev1/json/kudo-catalog.json) — 491 requisitos, 35 controles, 8 dominios.

Sheet Escala
A1: Puntuación | B1: Cumplimiento | C1: Nivel de Madurez | D1: Descripción
A2: 0 | B2: 0 | C2: No implementado | D2: El requisito no existe o no ha sido considerado.
A3: 1 | B3: 0.2 | C3: Inicial | D3: El requisito existe de manera reactiva o informal.
A4: 2 | B4: 0.4 | C4: Documentado | D4: El requisito está documentado y se aplica de forma consistente.
A5: 3 | B5: 0.6 | C5: Estandarizado | D5: El requisito está definido y se aplica de forma uniforme en la organización.
A6: 4 | B6: 0.8 | C6: Gestionado | D6: El requisito se mide mediante indicadores y existe evidencia de su gestión.
A7: 5 | B7: 1 | C7: Optimizado | D7: El requisito se mejora continuamente mediante métricas, automatización y retroalimentación.

Sheet Rangos de Madurez
A1: Cumplimiento mínimo | B1: Rango | C1: Nivel de Madurez | D1: Descripción
A2: 0 | B2: 0% – 19% | C2: Nivel 0 – Crítico | D2: La organización presenta un nivel de madurez crítico. Los procesos y controles de ciberseguridad son inexistentes o insuficientes para gestionar adecuadamente los riesgos. No existe un apetito de riesgo definido y las decisiones de negocio se toman sin considerar de forma estructurada la exposición al riesgo cibernético.
A3: 0.2 | B3: 20% – 39% | C3: Nivel 1 – Básico | D3: La organización cuenta con prácticas iniciales de ciberseguridad implementadas de forma reactiva o informal. El apetito de riesgo no se encuentra formalizado o es poco conocido, por lo que las decisiones de negocio suelen tomarse con información limitada sobre el riesgo cibernético.
A4: 0.4 | B4: 40% – 59% | C4: Nivel 2 – Operacional | D4: Existen procesos y controles documentados que se ejecutan de forma consistente, aunque con oportunidades de fortalecimiento. El apetito de riesgo comienza a utilizarse como referencia para la operación, pero las decisiones aún son mayoritariamente reactivas.
A5: 0.6 | B5: 60% – 79% | C5: Nivel 3 – Táctico | D5: Los procesos de ciberseguridad están definidos, documentados y estandarizados. La gestión del riesgo es consistente y las decisiones tácticas consideran el apetito de riesgo, aunque su aplicación aún no es uniforme en toda la organización.
A6: 0.8 | B6: 80% – 99% | C6: Nivel 4 – Estratégico | D6: La ciberseguridad se gestiona como un habilitador del negocio. Los controles son medidos y existe evidencia de su eficacia. El apetito de riesgo se utiliza para priorizar inversiones, definir excepciones y respaldar decisiones estratégicas de manera informada.
A7: 1 | B7: 100% | C7: Nivel 5 – Co-creación de Ciberseguridad | D7: La ciberseguridad forma parte de la estrategia y de la toma de decisiones del negocio. Existe mejora continua, automatización, métricas y una cultura de colaboración entre las áreas. El apetito de riesgo está claramente definido, es monitoreado continuamente y las decisiones de negocio consideran el impacto sobre el riesgo cibernético como un factor estratégico.

Sheet Cuestionario - Completo
A1: N° | B1: ID Dominio | C1: Dominio | D1: ID Control | E1: Control | F1: ID Requisito | G1: Requisito (Pregunta) | H1: Respuesta (0-5) | I1: % Cumplimiento | J1: Nivel de Madurez
A2: 1 | B2: ADR | C2: Análisis, Detección y Respuesta de Ciberseguridad | D2: ADR-1 | E2: Protección contra Software Malicioso | F2: ADR-1-req-1 | G2: Implementamos controles para prevenir, detectar y neutralizar amenazas provenientes de software malicioso en todos los sistemas de la organización. | I2: =IF(H2="","",H2/5) | J2: =IF(H2="","",VLOOKUP(H2,Escala!$A$2:$C$7,3,FALSE))
A3: 2 | B3: ADR | C3: Análisis, Detección y Respuesta de Ciberseguridad | D3: ADR-1 | E3: Protección contra Software Malicioso | F3: ADR-1-req-2 | G3: Desplegamos soluciones antimalware con capacidad de detección basada en comportamiento en endpoints, servidores y entornos cloud. | I3: =IF(H3="","",H3/5) | J3: =IF(H3="","",VLOOKUP(H3,Escala!$A$2:$C$7,3,FALSE))
A4: 3 | B4: ADR | C4: Análisis, Detección y Respuesta de Ciberseguridad | D4: ADR-1 | E4: Protección contra Software Malicioso | F4: ADR-1-req-3 | G4: Alertamos a los colaboradores ante comunicaciones sospechosas detectadas. | I4: =IF(H4="","",H4/5) | J4: =IF(H4="","",VLOOKUP(H4,Escala!$A$2:$C$7,3,FALSE))
A5: 4 | B5: ADR | C5: Análisis, Detección y Respuesta de Ciberseguridad | D5: ADR-1 | E5: Protección contra Software Malicioso | F5: ADR-1-req-4 | G5: Formamos adecuadamente a los usuarios en el reconocimiento y prevención de software malicioso como complemento a las protecciones técnicas implementadas. | I5: =IF(H5="","",H5/5) | J5: =IF(H5="","",VLOOKUP(H5,Escala!$A$2:$C$7,3,FALSE))
A6: 5 | B6: ADR | C6: Análisis, Detección y Respuesta de Ciberseguridad | D6: ADR-1 | E6: Protección contra Software Malicioso | F6: ADR-1-req-5 | G6: Controlamos el acceso a sitios web externos para reducir la exposición a contenido malicioso o no autorizado según la política de uso aceptable de la organización. | I6: =IF(H6="","",H6/5) | J6: =IF(H6="","",VLOOKUP(H6,Escala!$A$2:$C$7,3,FALSE))
A7: 6 | B7: ADR | C7: Análisis, Detección y Respuesta de Ciberseguridad | D7: ADR-1 | E7: Protección contra Software Malicioso | F7: ADR-1-req-6 | G7: Actualizamos continuamente las firmas y modelos de detección sin intervención manual. | I7: =IF(H7="","",H7/5) | J7: =IF(H7="","",VLOOKUP(H7,Escala!$A$2:$C$7,3,FALSE))
A8: 7 | B8: ADR | C8: Análisis, Detección y Respuesta de Ciberseguridad | D8: ADR-1 | E8: Protección contra Software Malicioso | F8: ADR-1-req-7 | G8: Analizamos los archivos en sandbox antes de su ejecución (detonación controlada). | I8: =IF(H8="","",H8/5) | J8: =IF(H8="","",VLOOKUP(H8,Escala!$A$2:$C$7,3,FALSE))
A9: 8 | B9: ADR | C9: Análisis, Detección y Respuesta de Ciberseguridad | D9: ADR-1 | E9: Protección contra Software Malicioso | F9: ADR-1-req-8 | G9: Detectamos técnicas de evasión avanzadas como fileless malware y living-off-the-land. | I9: =IF(H9="","",H9/5) | J9: =IF(H9="","",VLOOKUP(H9,Escala!$A$2:$C$7,3,FALSE))
A10: 9 | B10: ADR | C10: Análisis, Detección y Respuesta de Ciberseguridad | D10: ADR-1 | E10: Protección contra Software Malicioso | F10: ADR-1-req-9 | G10: Implementamos listas de control de aplicaciones autorizadas (whitelisting) en todos los sistemas. | I10: =IF(H10="","",H10/5) | J10: =IF(H10="","",VLOOKUP(H10,Escala!$A$2:$C$7,3,FALSE))
A11: 10 | B11: ADR | C11: Análisis, Detección y Respuesta de Ciberseguridad | D11: ADR-1 | E11: Protección contra Software Malicioso | F11: ADR-1-req-10 | G11: Aplicamos cuarentena automática ante la detección de amenazas en endpoints, servidores y entornos cloud. | I11: =IF(H11="","",H11/5) | J11: =IF(H11="","",VLOOKUP(H11,Escala!$A$2:$C$7,3,FALSE))
A12: 11 | B12: ADR | C12: Análisis, Detección y Respuesta de Ciberseguridad | D12: ADR-1 | E12: Protección contra Software Malicioso | F12: ADR-1-req-11 | G12: Protegemos el correo electrónico corporativo con análisis de adjuntos en sandbox y verificación de URLs mediante sistemas de reputación en tiempo real. | I12: =IF(H12="","",H12/5) | J12: =IF(H12="","",VLOOKUP(H12,Escala!$A$2:$C$7,3,FALSE))
A13: 12 | B13: ADR | C13: Análisis, Detección y Respuesta de Ciberseguridad | D13: ADR-1 | E13: Protección contra Software Malicioso | F13: ADR-1-req-12 | G13: Habilitamos DMARC, DKIM y SPF para la protección del correo electrónico contra phishing y suplantación. | I13: =IF(H13="","",H13/5) | J13: =IF(H13="","",VLOOKUP(H13,Escala!$A$2:$C$7,3,FALSE))
... A492: 491 | B492: THP | C492: Ciberseguridad en Talento Humano y Proveedores | D492: THP-4 | E492: Modelo de Responsabilidad Compartida en la Cadena de Suministro | F492: THP-4-req-17 | G492: Supervisamos, monitorizamos y revisamos las actividades de desarrollo de sistemas de información cuando estas sean realizadas por terceros externos. | I492: =IF(H492="","",H492/5) | J492: =IF(H492="","",VLOOKUP(H492,Escala!$A$2:$C$7,3,FALSE))

Sheet Resultado - Completo
B1: Resultado de Madurez — Cuestionario Completo
B3: Total de requisitos (n) | C3: 491
B4: Respuestas registradas | C4: =COUNT('Cuestionario - Completo'!$H$2:$H$492)
B5: Suma de puntos obtenidos (Σpi) | C5: =SUM('Cuestionario - Completo'!$H$2:$H$492)
B6: Puntos máximos posibles (5×n) | C6: =C3*5
B7: % de Madurez (M) | C7: =IF(C6=0,0,C5/C6)
B8: Nivel de Madurez | C8: =IF(C7="","",VLOOKUP(C7,'Rangos de Madurez'!$A$2:$C$7,3,TRUE))
B9: Descripción del nivel | C9: =IF(C7="","",VLOOKUP(C7,'Rangos de Madurez'!$A$2:$D$7,4,TRUE))
B12: Desglose por Dominio
B14: ID Dominio | C14: Dominio | D14: Requisitos | E14: Puntos Obtenidos | F14: Puntos Máximos | G14: % Madurez | H14: Nivel de Madurez
B15: ADR | C15: Análisis, Detección y Respuesta de Ciberseguridad | D15: =COUNTIF('Cuestionario - Completo'!$B$2:$B$492,"ADR") | E15: =SUMIF('Cuestionario - Completo'!$B$2:$B$492,"ADR",'Cuestionario - Completo'!$H$2:$H$492) | F15: =D15*5 | G15: =IF(F15=0,0,E15/F15) | H15: =IF(G15="","",VLOOKUP(G15,'Rangos de Madurez'!$A$2:$C$7,3,TRUE))
B16: CAP | C16: Ciberseguridad en Aplicaciones | D16: =COUNTIF('Cuestionario - Completo'!$B$2:$B$492,"CAP") | E16: =SUMIF('Cuestionario - Completo'!$B$2:$B$492,"CAP",'Cuestionario - Completo'!$H$2:$H$492) | F16: =D16*5 | G16: =IF(F16=0,0,E16/F16) | H16: =IF(G16="","",VLOOKUP(G16,'Rangos de Madurez'!$A$2:$C$7,3,TRUE))
B17: CCN | C17: Continuidad y Cambios del Negocio | D17: =COUNTIF('Cuestionario - Completo'!$B$2:$B$492,"CCN") | E17: =SUMIF('Cuestionario - Completo'!$B$2:$B$492,"CCN",'Cuestionario - Completo'!$H$2:$H$492) | F17: =D17*5 | G17: =IF(F17=0,0,E17/F17) | H17: =IF(G17="","",VLOOKUP(G17,'Rangos de Madurez'!$A$2:$C$7,3,TRUE))
B18: CIF | C18: Ciberseguridad en Infraestructura | D18: =COUNTIF('Cuestionario - Completo'!$B$2:$B$492,"CIF") | E18: =SUMIF('Cuestionario - Completo'!$B$2:$B$492,"CIF",'Cuestionario - Completo'!$H$2:$H$492) | F18: =D18*5 | G18: =IF(F18=0,0,E18/F18) | H18: =IF(G18="","",VLOOKUP(G18,'Rangos de Madurez'!$A$2:$C$7,3,TRUE))
B19: CIP | C19: Ciberseguridad en Identidad y Puntos Finales | D19: =COUNTIF('Cuestionario - Completo'!$B$2:$B$492,"CIP") | E19: =SUMIF('Cuestionario - Completo'!$B$2:$B$492,"CIP",'Cuestionario - Completo'!$H$2:$H$492) | F19: =D19*5 | G19: =IF(F19=0,0,E19/F19) | H19: =IF(G19="","",VLOOKUP(G19,'Rangos de Madurez'!$A$2:$C$7,3,TRUE))
B20: COR | C20: Coherencia Organizacional | D20: =COUNTIF('Cuestionario - Completo'!$B$2:$B$492,"COR") | E20: =SUMIF('Cuestionario - Completo'!$B$2:$B$492,"COR",'Cuestionario - Completo'!$H$2:$H$492) | F20: =D20*5 | G20: =IF(F20=0,0,E20/F20) | H20: =IF(G20="","",VLOOKUP(G20,'Rangos de Madurez'!$A$2:$C$7,3,TRUE))
B21: DIA | C21: Ciberseguridad en Datos e Inteligencia Artificial | D21: =COUNTIF('Cuestionario - Completo'!$B$2:$B$492,"DIA") | E21: =SUMIF('Cuestionario - Completo'!$B$2:$B$492,"DIA",'Cuestionario - Completo'!$H$2:$H$492) | F21: =D21*5 | G21: =IF(F21=0,0,E21/F21) | H21: =IF(G21="","",VLOOKUP(G21,'Rangos de Madurez'!$A$2:$C$7,3,TRUE))
B22: THP | C22: Ciberseguridad en Talento Humano y Proveedores | D22: =COUNTIF('Cuestionario - Completo'!$B$2:$B$492,"THP") | E22: =SUMIF('Cuestionario - Completo'!$B$2:$B$492,"THP",'Cuestionario - Completo'!$H$2:$H$492) | F22: =D22*5 | G22: =IF(F22=0,0,E22/F22) | H22: =IF(G22="","",VLOOKUP(G22,'Rangos de Madurez'!$A$2:$C$7,3,TRUE))

Sheet Cuestionario - Interno
B1: Cuestionario del ámbito Interno — pendiente
B3: Este cuestionario todavía no tiene definido el criterio de alcance por requisito (qué requisitos de los 491 aplican específicamente a este ámbito de gestión).
B4: Mientras se define ese criterio, utiliza la pestaña "Cuestionario - Completo", que ya incluye los 491 requisitos de los 8 dominios y su cálculo de madurez en la pestaña "Resultado - Completo".

Sheet Cuestionario - Terceros
B1: Cuestionario del ámbito Terceros — pendiente
B3: Este cuestionario todavía no tiene definido el criterio de alcance por requisito (qué requisitos de los 491 aplican específicamente a este ámbito de gestión).
B4: Mientras se define ese criterio, utiliza la pestaña "Cuestionario - Completo", que ya incluye los 491 requisitos de los 8 dominios y su cálculo de madurez en la pestaña "Resultado - Completo".

Sheet Cuestionario - Externo
B1: Cuestionario del ámbito Externo — pendiente
B3: Este cuestionario todavía no tiene definido el criterio de alcance por requisito (qué requisitos de los 491 aplican específicamente a este ámbito de gestión).
B4: Mientras se define ese criterio, utiliza la pestaña "Cuestionario - Completo", que ya incluye los 491 requisitos de los 8 dominios y su cálculo de madurez en la pestaña "Resultado - Completo".
